robocorp/excel/__init__.py
robocorp/excel/_types.py
robocorp/excel/_workbooks.py
robocorp/excel/excel.py
robocorp/excel/py.typed
robocorp/excel/tables.py
robocorp/excel/workbook.py
robocorp/excel/worksheet.py
robocorp_excel-0.4.5.dist-info/METADATA
robocorp_excel-0.4.5.dist-info/WHEEL
robocorp_excel-0.4.5.dist-info/RECORD
