Metadata-Version: 2.1
Name: robocorp-excel
Version: 0.4.5
Summary: Robocorp Excel automation library
Home-page: https://github.com/robocorp/robocorp/
License: Apache-2.0
Author: Fabio Z.
Author-email: fabio@robocorp.com
Requires-Python: >=3.9,<4.0
Classifier: License :: OSI Approved :: Apache Software License
Classifier: Programming Language :: Python :: 3
Classifier: Programming Language :: Python :: 3.9
Classifier: Programming Language :: Python :: 3.10
Classifier: Programming Language :: Python :: 3.11
Classifier: Programming Language :: Python :: 3.12
Requires-Dist: openpyxl (>=3.0.9,<4.0.0)
Requires-Dist: pillow (>=9.1.1,<11.0.0)
Requires-Dist: types-openpyxl (>=3.1.5.20240918,<4.0.0.0)
Requires-Dist: typing-extensions (>=4.5.0,<5.0.0)
Requires-Dist: xlrd (>=2.0.1,<3.0.0)
Requires-Dist: xlutils (>=2.0.0,<3.0.0)
Requires-Dist: xlwt (>=1.3.0,<2.0.0)
Project-URL: Repository, https://github.com/robocorp/robocorp/
